{"DIGITAL Command Language":["jmdugan/blocklists"],"null":["1dv612-test3/test-repo","mmmonteiro/designethics","bnb/awesome-developer-streams","jwasham/coding-interview-university","1c7/chinese-independent-developer","sindresorhus/awesome","aikorea/awesome-rl","stereobooster/css-in-js-101"],"JavaScript":["kamranahmedse/driver.js","pinterest/gestalt","pshihn/rough","BrainJS/brain.js","LeCoupa/awesome-cheatsheets","kentcdodds/react-testing-library","eveningkid/reacto","vuejs/vue","nhnent/tui.chart","jaredreich/pell","rcaferati/react-native-really-awesome-button","coderitual/bounty","hakimel/reveal.js","chaozh/awesome-blockchain-cn","GoogleChrome/puppeteer","jondot/hygen","mdbootstrap/bootstrap-material-design"],"Python":["ashnkumar/sketch-code","StevenBlack/hosts","UltimateHackers/hue","arunmallya/packnet","scikit-learn/scikit-learn","ambv/black","crista/exercises-in-programming-style","mm-mansour/Fast-Pandas","timgrossmann/InstaPy","nvbn/thefuck","artetxem/undreamt"],"Swift":["watson-developer-cloud/visual-recognition-coreml","sindresorhus/gifski-app"],"C++":["agnusmaximus/Word2Bits","tensorflow/tensorflow","NervanaSystems/ngraph"],"TypeScript":["jacobbogers/libRmath.js","oclif/oclif","witheve/Eve","Jigsaw-Code/outline-server","mgechev/mlx"],"Ruby":["jondot/awesome-react-native"],"Jupyter Notebook":["fivethirtyeight/data","zotroneneis/machine_learning_basics","ilkarman/DeepLearningFrameworks"],"C":["saleemrashid/ledger-mcu-backdoor","torvalds/linux","jakogut/tinyvm"],"TeX":["joaoventura/full-speed-python"],"Go":["jenkins-x/jx","solo-io/gloo","iawia002/annie","kubernetes/kubernetes","mlabouardy/komiser"],"R":["clauswilke/dataviz"],"C#":["intel/acat","Unity-Technologies/EntityComponentSystemSamples"],"Kotlin":["ktorio/ktor","TonnyL/Spark","JetBrains/kotlin-native"],"Shell":["jochemin/raspnode","robbyrussell/oh-my-zsh","htruong/crankshaft"],"Java":["signalapp/Signal-Android","DerDeterminist/XCOM","JakeWharton/RxRelay"],"CSS":["udacity/course-collaboration-travel-plans","tachyons-css/tachyons"],"Dart":["flutter/flutter"],"Rust":["g-plane/zsh-yarn-autocompletions"]}