{"Java":["monkeyWie/proxyee-down","Wechat-Group/weixin-java-tools"],"JavaScript":["quickappdev/awesome-quickapp","drcmda/react-spring","appbaseio/dejavu","facebook/create-react-app","kamranahmedse/driver.js","nodejs/node","rematch/rematch","BrainJS/brain.js","JoshuaWise/better-sqlite3","airbnb/javascript","gatsbyjs/gatsby","d3/d3","Semantic-Org/Semantic-UI","RocketChat/Rocket.Chat","answershuto/learnVue","TowhidKashem/reddit-client-app"],"null":["CyC2018/Interview-Notebook","1c7/chinese-independent-developer","xitu/tensorflow-docs","LyndonChin/kotlin-docs-zh","kelseyhightower/nocode","rShetty/awesome-podcasts","sindresorhus/awesome"],"TeX":["joaoventura/full-speed-python"],"C#":["Unity-Technologies/UnityCsReference","aspnet/Blazor"],"Go":["claudiodangelis/qr-filetransfer","iawia002/annie","bzppx/bzppx-codepub","golang/dep"],"Python":["victoresque/pytorch-template","google/upvote","marcosfede/algorithms","tensorflow/models","toddmotto/public-apis","vinta/awesome-python","django/django","rg3/youtube-dl","ceruleanacg/Personae","soimort/you-get","keras-team/keras"],"Jupyter Notebook":["higgsfield/RL-Adventure","ageron/handson-ml"],"C++":["electron/electron","tensorflow/tensorflow"],"Swift":["shaps80/Peek"],"HTML":["i5ting/How-to-learn-node-correctly","luyishisi/Anti-Anti-Spider"],"Rust":["sharkdp/hyperfine"],"C":["spacehuhn/esp8266_deauther","firehol/netdata","torvalds/linux"],"CSS":["twbs/bootstrap"],"TypeScript":["Jigsaw-Code/outline-server","oclif/oclif","angular/angular"],"Vue":["syuilo/misskey"],"Shell":["chrissimpkins/Crunch"]}